pyturtleorbit/setup.py
pyturtleorbit-1.2.3.dist-info/METADATA
pyturtleorbit-1.2.3.dist-info/WHEEL
pyturtleorbit-1.2.3.dist-info/top_level.txt
pyturtleorbit-1.2.3.dist-info/RECORD
