Metadata-Version: 2.1
Name: pyturtleorbit
Version: 1.2.3
Summary: A package for orbiting turtles in python
Home-page: https://repl.it/@SeamusDonahue/pyorbit#pyorbit_project/setup.py
Author: Seamus Donahue
Author-email: thedarkknite10@gmail.com
License: UNKNOWN
Platform: UNKNOWN
Classifier: Programming Language :: Python :: 3
Classifier: License :: OSI Approved :: MIT License
Classifier: Operating System :: OS Independent
Requires-Python: >=3.6
